mbpy/__about__.py
mbpy/__init__.py
mbpy/chars.py
mbpy/cli.py
mbpy/cmd.py
mbpy/collect.py
mbpy/create.py
mbpy/ctx.py
mbpy/docparser.py
mbpy/grammar.py
mbpy/heartbeat.py
mbpy/import_utils.py
mbpy/log.py
mbpy/main.py
mbpy/mbconvert.py
mbpy/parse.py
mbpy/plugin.py
mbpy/proxy2.py
mbpy/rag.py
mbpy/sock.py
mbpy/test_mbconvert.py
mbpy/test_system.py
mbpy/uv.py
mbpy/bench/__init__.py
mbpy/bench/echoclient.py
mbpy/bench/echoserver.py
mbpy/bench/rlserver.py
mbpy/diff/__init__.py
mbpy/diff/core.py
mbpy/diff/diff.py
mbpy/diff/tests/__init__.py
mbpy/diff/tests/conftest.py
mbpy/diff/tests/test_core.py
mbpy/diff/tests/test_ui.py
mbpy/expect/__init__.py
mbpy/expect/aio.py
mbpy/expect/asyncspawn.py
mbpy/expect/exceptions.py
mbpy/expect/expect.py
mbpy/expect/pop.py
mbpy/expect/repl.py
mbpy/expect/searcher.py
mbpy/expect/spawn.py
mbpy/expect/spawnbase.py
mbpy/expect/utils.py
mbpy/helpers/__init__.py
mbpy/helpers/_acmd.py
mbpy/helpers/_cache.py
mbpy/helpers/_clean.py
mbpy/helpers/_cmd.py
mbpy/helpers/_compile.py
mbpy/helpers/_compile_cmd.py
mbpy/helpers/_display.py
mbpy/helpers/_dist.py
mbpy/helpers/_env.py
mbpy/helpers/_find.py
mbpy/helpers/_getopt.py
mbpy/helpers/_git_ctx.py
mbpy/helpers/_logging.py
mbpy/helpers/_lru.py
mbpy/helpers/_modified.py
mbpy/helpers/_naming.py
mbpy/helpers/_proto.py
mbpy/helpers/_search.py
mbpy/helpers/_setup.py
mbpy/helpers/_setup_py.py
mbpy/helpers/_show.py
mbpy/helpers/_spawn.py
mbpy/helpers/_sphinx.py
mbpy/helpers/_static.py
mbpy/helpers/_traceback.py
mbpy/helpers/_typing.py
mbpy/helpers/autopip.py
mbpy/helpers/cli.py
mbpy/helpers/gcliff.py
mbpy/helpers/gcommit.py
mbpy/helpers/traverse.py
mbpy/helpers/xmltodict.py
mbpy/helpers/_mypy/__init__.py
mbpy/helpers/_mypy/_array.py
mbpy/helpers/_mypy/_dataclass.py
mbpy/helpers/_mypy/_git.py
mbpy/helpers/_mypy/_metastore.py
mbpy/helpers/_mypy/_typed_dict.py
mbpy/helpers/_mypy/diff-cache.py
mbpy/helpers/_mypy/fastparse.py
mbpy/helpers/_mypy/fscache.py
mbpy/helpers/_mypy/fswatcher.py
mbpy-2.0.18.dist-info/METADATA
mbpy-2.0.18.dist-info/WHEEL
mbpy-2.0.18.dist-info/entry_points.txt
mbpy-2.0.18.dist-info/top_level.txt
mbpy-2.0.18.dist-info/RECORD
