Metadata-Version: 2.2
Name: mbpy
Version: 2.0.18
Classifier: Development Status :: 5 - Production/Stable
Classifier: Environment :: Console
Classifier: Intended Audience :: Developers
Classifier: Programming Language :: Python :: 3.8
Classifier: Programming Language :: Python :: 3.9
Classifier: Programming Language :: Python :: 3.10
Classifier: Programming Language :: Python :: 3.11
Classifier: Programming Language :: Python :: 3.12
Classifier: Programming Language :: Python :: 3.13
Classifier: Programming Language :: Python :: 3 :: Only
Classifier: Programming Language :: Python :: Implementation :: CPython
Classifier: Programming Language :: Cython
Classifier: License :: OSI Approved :: MIT License
Classifier: Operating System :: OS Independent
Requires-Python: >=3.10
Requires-Dist: mrender>=1.0.218
Requires-Dist: tomlkit>=0.13.2
Requires-Dist: aiofiles>=24.1.0
Requires-Dist: pybind11>=2.13.6
Requires-Dist: jinja2>=3.1.5
Requires-Dist: distro>=1.9.0
Requires-Dist: attrs>=24.3.0
Requires-Dist: h11>=0.14.0
Requires-Dist: regex>=2024.11.6
Requires-Dist: fastjsonschema>=2.21.1
Requires-Dist: multidict>=6.1.0
Requires-Dist: greenlet>=3.1.1
Requires-Dist: toml>=0.10.2
Requires-Dist: pathspec>=0.12.1
Requires-Dist: coverage>=7.6.10
Requires-Dist: beautifulsoup4>=4.12.3
Requires-Dist: mypy>=1.14.1
Requires-Dist: markdown>=3.0.0
Requires-Dist: keyring>=25.6.0
Requires-Dist: frozenlist>=1.5.0
Requires-Dist: filelock>=3.16.1
Requires-Dist: more-itertools>=10.5.0
Requires-Dist: twine>=6.0.1
Requires-Dist: certifi>=2024.12.14
Requires-Dist: pytest>=8.3.4
Requires-Dist: yarl>=1.18.3
Requires-Dist: requests>=2.32.3
Requires-Dist: zstandard>=0.23.0
Requires-Dist: anyio>=4.8.0
Requires-Dist: numpy>=2.2.1
Requires-Dist: urllib3>=2.3.0
Requires-Dist: markupsafe>=3.0.2
Requires-Dist: joblib>=1.4.2
Requires-Dist: idna>=3.10
Requires-Dist: openai>=1.59.7
Requires-Dist: python-dateutil>=2.9.0.post0
Requires-Dist: aiohttp>=3.11.11
Requires-Dist: packaging>=24.2
Requires-Dist: setuptools>=75.8.0
Requires-Dist: click>=8.1.8
Requires-Dist: tomli-w>=1.1.0
Requires-Dist: lark>=1.2.2
Requires-Dist: six>=1.17.0
Requires-Dist: tqdm>=4.67.1
Requires-Dist: cython>=3.0.11
Requires-Dist: distlib>=0.3.9
Requires-Dist: pkginfo>=1.12.0
Requires-Dist: playwright>=1.49.1
Requires-Dist: nltk>=3.9.1
Requires-Dist: httpcore>=1.0.7
Requires-Dist: platformdirs>=4.3.6
Requires-Dist: httpx>=0.28.1
Requires-Dist: docutils>=0.21.2
Requires-Dist: networkx>=3.4.2
Requires-Dist: soupsieve>=2.6
Requires-Dist: charset-normalizer>=3.4.1
Requires-Dist: pytest-cov>=6.0.0
Requires-Dist: python-dotenv>=1.0.1
Requires-Dist: iniconfig>=2.0.0
Requires-Dist: uvloop>=0.21.0
Requires-Dist: aiostream>=0.6.4
Requires-Dist: rich>=13.9.4
Provides-Extra: cython
Requires-Dist: cython>=3.0.11; extra == "cython"
Provides-Extra: dev
Requires-Dist: pytest-asyncio>=0.25.0; extra == "dev"
Requires-Dist: textual>=1.0.0; extra == "dev"
Provides-Extra: extras
Requires-Dist: uvloop>=0.21.0; extra == "extras"
Requires-Dist: aiofiles==24.1.0; extra == "extras"
Requires-Dist: diskcache>=5.6.3; extra == "extras"
Requires-Dist: lxml; extra == "extras"
Requires-Dist: more-itertools>=10.5.0; extra == "extras"
Requires-Dist: requests>=2.26.0; extra == "extras"
Requires-Dist: rich-click>=1.8.3; extra == "extras"
Requires-Dist: tomlkit>=0.12.0; extra == "extras"
Provides-Extra: mkdocs
Requires-Dist: mkdocs>=1.6.1; extra == "mkdocs"
Requires-Dist: mkdocs-material>=9.5.42; extra == "mkdocs"
Requires-Dist: mkdocs>=1.6.1; extra == "mkdocs"
Requires-Dist: mkdocstrings>=0.24.3; extra == "mkdocs"
Provides-Extra: perf
Requires-Dist: aiohttp>=3.11.11; extra == "perf"
Requires-Dist: orjson>=3.10.12; extra == "perf"
Requires-Dist: uvloop>=0.21.0; extra == "perf"
Provides-Extra: profile
Requires-Dist: psutil>=6.1.1; extra == "profile"
Requires-Dist: pynvml>=12.0.0; extra == "profile"
Provides-Extra: sphinx
Requires-Dist: sphinxcontrib-napoleon>=0.7; extra == "sphinx"
Requires-Dist: sphinx>=8.1.3; extra == "sphinx"
Requires-Dist: furo; extra == "sphinx"
Requires-Dist: sphinx-tippy>=0.4.3; extra == "sphinx"
Requires-Dist: sphinx>=6.2.1; extra == "sphinx"
Requires-Dist: sphinx-autodoc2>=0.5.0; extra == "sphinx"
Requires-Dist: sphinx-design>=0.5.0; extra == "sphinx"
Provides-Extra: all
Requires-Dist: mrender>=1.0.218; extra == "all"
Requires-Dist: tomlkit>=0.13.2; extra == "all"
Requires-Dist: aiofiles>=24.1.0; extra == "all"
Requires-Dist: pybind11>=2.13.6; extra == "all"
Requires-Dist: jinja2>=3.1.5; extra == "all"
Requires-Dist: distro>=1.9.0; extra == "all"
Requires-Dist: attrs>=24.3.0; extra == "all"
Requires-Dist: h11>=0.14.0; extra == "all"
Requires-Dist: regex>=2024.11.6; extra == "all"
Requires-Dist: fastjsonschema>=2.21.1; extra == "all"
Requires-Dist: multidict>=6.1.0; extra == "all"
Requires-Dist: greenlet>=3.1.1; extra == "all"
Requires-Dist: toml>=0.10.2; extra == "all"
Requires-Dist: pathspec>=0.12.1; extra == "all"
Requires-Dist: coverage>=7.6.10; extra == "all"
Requires-Dist: beautifulsoup4>=4.12.3; extra == "all"
Requires-Dist: mypy>=1.14.1; extra == "all"
Requires-Dist: markdown>=3.0.0; extra == "all"
Requires-Dist: keyring>=25.6.0; extra == "all"
Requires-Dist: frozenlist>=1.5.0; extra == "all"
Requires-Dist: filelock>=3.16.1; extra == "all"
Requires-Dist: more-itertools>=10.5.0; extra == "all"
Requires-Dist: twine>=6.0.1; extra == "all"
Requires-Dist: certifi>=2024.12.14; extra == "all"
Requires-Dist: pytest>=8.3.4; extra == "all"
Requires-Dist: yarl>=1.18.3; extra == "all"
Requires-Dist: requests>=2.32.3; extra == "all"
Requires-Dist: zstandard>=0.23.0; extra == "all"
Requires-Dist: anyio>=4.8.0; extra == "all"
Requires-Dist: numpy>=2.2.1; extra == "all"
Requires-Dist: urllib3>=2.3.0; extra == "all"
Requires-Dist: markupsafe>=3.0.2; extra == "all"
Requires-Dist: joblib>=1.4.2; extra == "all"
Requires-Dist: idna>=3.10; extra == "all"
Requires-Dist: openai>=1.59.7; extra == "all"
Requires-Dist: python-dateutil>=2.9.0.post0; extra == "all"
Requires-Dist: aiohttp>=3.11.11; extra == "all"
Requires-Dist: packaging>=24.2; extra == "all"
Requires-Dist: setuptools>=75.8.0; extra == "all"
Requires-Dist: click>=8.1.8; extra == "all"
Requires-Dist: tomli-w>=1.1.0; extra == "all"
Requires-Dist: lark>=1.2.2; extra == "all"
Requires-Dist: six>=1.17.0; extra == "all"
Requires-Dist: tqdm>=4.67.1; extra == "all"
Requires-Dist: cython>=3.0.11; extra == "all"
Requires-Dist: distlib>=0.3.9; extra == "all"
Requires-Dist: pkginfo>=1.12.0; extra == "all"
Requires-Dist: playwright>=1.49.1; extra == "all"
Requires-Dist: nltk>=3.9.1; extra == "all"
Requires-Dist: httpcore>=1.0.7; extra == "all"
Requires-Dist: platformdirs>=4.3.6; extra == "all"
Requires-Dist: httpx>=0.28.1; extra == "all"
Requires-Dist: docutils>=0.21.2; extra == "all"
Requires-Dist: networkx>=3.4.2; extra == "all"
Requires-Dist: soupsieve>=2.6; extra == "all"
Requires-Dist: charset-normalizer>=3.4.1; extra == "all"
Requires-Dist: pytest-cov>=6.0.0; extra == "all"
Requires-Dist: python-dotenv>=1.0.1; extra == "all"
Requires-Dist: iniconfig>=2.0.0; extra == "all"
Requires-Dist: uvloop>=0.21.0; extra == "all"
Requires-Dist: aiostream>=0.6.4; extra == "all"
Requires-Dist: sphinxcontrib-napoleon>=0.7; extra == "all"
Requires-Dist: furo>=2024.8.6; extra == "all"
Requires-Dist: sphinx>=8.1.3; extra == "all"
Requires-Dist: rich>=13.9.4; extra == "all"
